<?xml version="1.0" encoding="UTF-8"?>
<sv:node sv:name="tour-type" xmlns:sv="http://www.jcp.org/jcr/sv/1.0" xmlns:xsi="http://www.w3.org/2001/XMLSchema-instance">
  <sv:property sv:name="jcr:primaryType" sv:type="Name">
    <sv:value>mgnl:page</sv:value>
  </sv:property>
  <sv:property sv:name="jcr:uuid" sv:type="String">
    <sv:value>05872876-073e-40a3-a3c5-0d0a18c1d43d</sv:value>
  </sv:property>
  <sv:property sv:name="hideInNav" sv:type="Boolean">
    <sv:value>false</sv:value>
  </sv:property>
  <sv:property sv:name="jcr:createdBy" sv:type="String">
    <sv:value>admin</sv:value>
  </sv:property>
  <sv:property sv:name="mgnl:activationStatus" sv:type="Boolean">
    <sv:value>true</sv:value>
  </sv:property>
  <sv:property sv:name="mgnl:created" sv:type="Date">
    <sv:value>2015-01-27T13:21:08.859+01:00</sv:value>
  </sv:property>
  <sv:property sv:name="mgnl:createdBy" sv:type="String">
    <sv:value>superuser</sv:value>
  </sv:property>
  <sv:property sv:name="mgnl:lastActivated" sv:type="Date">
    <sv:value>2015-10-27T13:40:43.315+01:00</sv:value>
  </sv:property>
  <sv:property sv:name="mgnl:lastActivatedBy" sv:type="String">
    <sv:value>superuser</sv:value>
  </sv:property>
  <sv:property sv:name="mgnl:lastModified" sv:type="Date">
    <sv:value>2015-10-27T10:41:44.110+01:00</sv:value>
  </sv:property>
  <sv:property sv:name="mgnl:lastModifiedBy" sv:type="String">
    <sv:value>superuser</sv:value>
  </sv:property>
  <sv:property sv:name="mgnl:template" sv:type="String">
    <sv:value>tours:pages/categoryOverview</sv:value>
  </sv:property>
  <sv:property sv:name="navigationTitle" sv:type="String">
    <sv:value>Tours</sv:value>
  </sv:property>
  <sv:property sv:name="title" sv:type="String">
    <sv:value>Tour Types</sv:value>
  </sv:property>
  <sv:node sv:name="main">
    <sv:property sv:name="jcr:primaryType" sv:type="Name">
      <sv:value>mgnl:area</sv:value>
    </sv:property>
    <sv:property sv:name="jcr:uuid" sv:type="String">
      <sv:value>65f66aac-c0aa-42b4-b6a9-1f749a6429b0</sv:value>
    </sv:property>
    <sv:property sv:name="jcr:createdBy" sv:type="String">
      <sv:value>admin</sv:value>
    </sv:property>
    <sv:property sv:name="mgnl:activationStatus" sv:type="Boolean">
      <sv:value>true</sv:value>
    </sv:property>
    <sv:property sv:name="mgnl:created" sv:type="Date">
      <sv:value>2015-01-27T13:21:12.019+01:00</sv:value>
    </sv:property>
    <sv:property sv:name="mgnl:createdBy" sv:type="String">
      <sv:value>superuser</sv:value>
    </sv:property>
    <sv:property sv:name="mgnl:lastActivated" sv:type="Date">
      <sv:value>2015-10-27T13:40:43.315+01:00</sv:value>
    </sv:property>
    <sv:property sv:name="mgnl:lastActivatedBy" sv:type="String">
      <sv:value>superuser</sv:value>
    </sv:property>
    <sv:property sv:name="mgnl:lastModified" sv:type="Date">
      <sv:value>2015-10-27T10:41:44.110+01:00</sv:value>
    </sv:property>
    <sv:property sv:name="mgnl:lastModifiedBy" sv:type="String">
      <sv:value>superuser</sv:value>
    </sv:property>
    <sv:node sv:name="0">
      <sv:property sv:name="jcr:primaryType" sv:type="Name">
        <sv:value>mgnl:component</sv:value>
      </sv:property>
      <sv:property sv:name="jcr:uuid" sv:type="String">
        <sv:value>e4519798-0df3-4b79-92b9-5686b2c3c17b</sv:value>
      </sv:property>
      <sv:property sv:name="jcr:createdBy" sv:type="String">
        <sv:value>admin</sv:value>
      </sv:property>
      <sv:property sv:name="mgnl:activationStatus" sv:type="Boolean">
        <sv:value>true</sv:value>
      </sv:property>
      <sv:property sv:name="mgnl:created" sv:type="Date">
        <sv:value>2015-01-28T16:47:31.831+01:00</sv:value>
      </sv:property>
      <sv:property sv:name="mgnl:createdBy" sv:type="String">
        <sv:value>superuser</sv:value>
      </sv:property>
      <sv:property sv:name="mgnl:lastActivated" sv:type="Date">
        <sv:value>2015-10-27T13:40:43.315+01:00</sv:value>
      </sv:property>
      <sv:property sv:name="mgnl:lastActivatedBy" sv:type="String">
        <sv:value>superuser</sv:value>
      </sv:property>
      <sv:property sv:name="mgnl:lastModified" sv:type="Date">
        <sv:value>2015-01-28T16:47:31.831+01:00</sv:value>
      </sv:property>
      <sv:property sv:name="mgnl:lastModifiedBy" sv:type="String">
        <sv:value>superuser</sv:value>
      </sv:property>
      <sv:property sv:name="mgnl:template" sv:type="String">
        <sv:value>tours:components/tourTypeOverviewHeader</sv:value>
      </sv:property>
    </sv:node>
    <sv:node sv:name="01">
      <sv:property sv:name="jcr:primaryType" sv:type="Name">
        <sv:value>mgnl:component</sv:value>
      </sv:property>
      <sv:property sv:name="jcr:uuid" sv:type="String">
        <sv:value>3193937f-8216-4dfc-a5db-16e0ef9f9c00</sv:value>
      </sv:property>
      <sv:property sv:name="jcr:createdBy" sv:type="String">
        <sv:value>admin</sv:value>
      </sv:property>
      <sv:property sv:name="mgnl:activationStatus" sv:type="Boolean">
        <sv:value>true</sv:value>
      </sv:property>
      <sv:property sv:name="mgnl:created" sv:type="Date">
        <sv:value>2015-01-29T22:24:50.086+01:00</sv:value>
      </sv:property>
      <sv:property sv:name="mgnl:createdBy" sv:type="String">
        <sv:value>superuser</sv:value>
      </sv:property>
      <sv:property sv:name="mgnl:lastActivated" sv:type="Date">
        <sv:value>2015-10-27T13:40:43.315+01:00</sv:value>
      </sv:property>
      <sv:property sv:name="mgnl:lastActivatedBy" sv:type="String">
        <sv:value>superuser</sv:value>
      </sv:property>
      <sv:property sv:name="mgnl:lastModified" sv:type="Date">
        <sv:value>2015-01-29T22:24:50.086+01:00</sv:value>
      </sv:property>
      <sv:property sv:name="mgnl:lastModifiedBy" sv:type="String">
        <sv:value>superuser</sv:value>
      </sv:property>
      <sv:property sv:name="mgnl:template" sv:type="String">
        <sv:value>tours:components/tourListFeaturedRow</sv:value>
      </sv:property>
    </sv:node>
    <sv:node sv:name="02">
      <sv:property sv:name="jcr:primaryType" sv:type="Name">
        <sv:value>mgnl:component</sv:value>
      </sv:property>
      <sv:property sv:name="jcr:uuid" sv:type="String">
        <sv:value>98514262-eaf1-45ed-b30d-fdd041d2270b</sv:value>
      </sv:property>
      <sv:property sv:name="floating" sv:type="String">
        <sv:value>true</sv:value>
      </sv:property>
      <sv:property sv:name="jcr:createdBy" sv:type="String">
        <sv:value>admin</sv:value>
      </sv:property>
      <sv:property sv:name="mgnl:activationStatus" sv:type="Boolean">
        <sv:value>true</sv:value>
      </sv:property>
      <sv:property sv:name="mgnl:created" sv:type="Date">
        <sv:value>2015-10-27T10:41:07.164+01:00</sv:value>
      </sv:property>
      <sv:property sv:name="mgnl:createdBy" sv:type="String">
        <sv:value>superuser</sv:value>
      </sv:property>
      <sv:property sv:name="mgnl:lastActivated" sv:type="Date">
        <sv:value>2015-10-27T13:40:43.315+01:00</sv:value>
      </sv:property>
      <sv:property sv:name="mgnl:lastActivatedBy" sv:type="String">
        <sv:value>superuser</sv:value>
      </sv:property>
      <sv:property sv:name="mgnl:lastModified" sv:type="Date">
        <sv:value>2015-10-27T10:41:44.110+01:00</sv:value>
      </sv:property>
      <sv:property sv:name="mgnl:lastModifiedBy" sv:type="String">
        <sv:value>superuser</sv:value>
      </sv:property>
      <sv:property sv:name="mgnl:template" sv:type="String">
        <sv:value>travel-demo:components/social</sv:value>
      </sv:property>
      <sv:property sv:name="rounded" sv:type="String">
        <sv:value>false</sv:value>
      </sv:property>
      <sv:property sv:name="services" sv:type="String" sv:multiple="true">
        <sv:value>twitter</sv:value>
        <sv:value>facebook</sv:value>
        <sv:value>google_plus</sv:value>
      </sv:property>
      <sv:property sv:name="size" sv:type="String">
        <sv:value>32</sv:value>
      </sv:property>
      <sv:property sv:name="vertical" sv:type="String">
        <sv:value>true</sv:value>
      </sv:property>
    </sv:node>
    <sv:node sv:name="00">
      <sv:property sv:name="jcr:primaryType" sv:type="Name">
        <sv:value>mgnl:component</sv:value>
      </sv:property>
      <sv:property sv:name="jcr:uuid" sv:type="String">
        <sv:value>a835f66f-6d45-41f6-8e6e-8163a1ef79a8</sv:value>
      </sv:property>
      <sv:property sv:name="jcr:createdBy" sv:type="String">
        <sv:value>admin</sv:value>
      </sv:property>
      <sv:property sv:name="mgnl:activationStatus" sv:type="Boolean">
        <sv:value>true</sv:value>
      </sv:property>
      <sv:property sv:name="mgnl:created" sv:type="Date">
        <sv:value>2015-01-29T16:46:43.704+01:00</sv:value>
      </sv:property>
      <sv:property sv:name="mgnl:createdBy" sv:type="String">
        <sv:value>superuser</sv:value>
      </sv:property>
      <sv:property sv:name="mgnl:lastActivated" sv:type="Date">
        <sv:value>2015-10-27T13:40:43.317+01:00</sv:value>
      </sv:property>
      <sv:property sv:name="mgnl:lastActivatedBy" sv:type="String">
        <sv:value>superuser</sv:value>
      </sv:property>
      <sv:property sv:name="mgnl:lastModified" sv:type="Date">
        <sv:value>2015-01-29T16:46:43.704+01:00</sv:value>
      </sv:property>
      <sv:property sv:name="mgnl:lastModifiedBy" sv:type="String">
        <sv:value>superuser</sv:value>
      </sv:property>
      <sv:property sv:name="mgnl:template" sv:type="String">
        <sv:value>tours:components/tourList</sv:value>
      </sv:property>
    </sv:node>
  </sv:node>
  <sv:node sv:name="footer">
    <sv:property sv:name="jcr:primaryType" sv:type="Name">
      <sv:value>mgnl:area</sv:value>
    </sv:property>
    <sv:property sv:name="jcr:uuid" sv:type="String">
      <sv:value>12f26132-0381-465f-8d13-155cc3bb4669</sv:value>
    </sv:property>
    <sv:property sv:name="jcr:createdBy" sv:type="String">
      <sv:value>admin</sv:value>
    </sv:property>
    <sv:property sv:name="mgnl:activationStatus" sv:type="Boolean">
      <sv:value>true</sv:value>
    </sv:property>
    <sv:property sv:name="mgnl:created" sv:type="Date">
      <sv:value>2015-02-26T16:14:31.940+01:00</sv:value>
    </sv:property>
    <sv:property sv:name="mgnl:createdBy" sv:type="String">
      <sv:value>superuser</sv:value>
    </sv:property>
    <sv:property sv:name="mgnl:lastActivated" sv:type="Date">
      <sv:value>2015-10-27T13:40:43.318+01:00</sv:value>
    </sv:property>
    <sv:property sv:name="mgnl:lastActivatedBy" sv:type="String">
      <sv:value>superuser</sv:value>
    </sv:property>
    <sv:property sv:name="mgnl:lastModified" sv:type="Date">
      <sv:value>2015-06-18T17:22:48.868+02:00</sv:value>
    </sv:property>
    <sv:property sv:name="mgnl:lastModifiedBy" sv:type="String">
      <sv:value>superuser</sv:value>
    </sv:property>
    <sv:node sv:name="footer1">
      <sv:property sv:name="jcr:primaryType" sv:type="Name">
        <sv:value>mgnl:area</sv:value>
      </sv:property>
      <sv:property sv:name="jcr:uuid" sv:type="String">
        <sv:value>7af2d089-e07d-48f3-aa27-12710370a9a1</sv:value>
      </sv:property>
      <sv:property sv:name="jcr:createdBy" sv:type="String">
        <sv:value>admin</sv:value>
      </sv:property>
      <sv:property sv:name="mgnl:activationStatus" sv:type="Boolean">
        <sv:value>true</sv:value>
      </sv:property>
      <sv:property sv:name="mgnl:created" sv:type="Date">
        <sv:value>2015-02-26T16:14:31.955+01:00</sv:value>
      </sv:property>
      <sv:property sv:name="mgnl:createdBy" sv:type="String">
        <sv:value>superuser</sv:value>
      </sv:property>
      <sv:property sv:name="mgnl:lastActivated" sv:type="Date">
        <sv:value>2015-10-27T13:40:43.318+01:00</sv:value>
      </sv:property>
      <sv:property sv:name="mgnl:lastActivatedBy" sv:type="String">
        <sv:value>superuser</sv:value>
      </sv:property>
      <sv:property sv:name="mgnl:lastModified" sv:type="Date">
        <sv:value>2015-02-26T16:14:31.955+01:00</sv:value>
      </sv:property>
      <sv:property sv:name="mgnl:lastModifiedBy" sv:type="String">
        <sv:value>superuser</sv:value>
      </sv:property>
    </sv:node>
    <sv:node sv:name="footer2">
      <sv:property sv:name="jcr:primaryType" sv:type="Name">
        <sv:value>mgnl:area</sv:value>
      </sv:property>
      <sv:property sv:name="jcr:uuid" sv:type="String">
        <sv:value>bef2cd3e-ac68-4ad7-ae31-8b791e2729e0</sv:value>
      </sv:property>
      <sv:property sv:name="jcr:createdBy" sv:type="String">
        <sv:value>admin</sv:value>
      </sv:property>
      <sv:property sv:name="mgnl:activationStatus" sv:type="Boolean">
        <sv:value>true</sv:value>
      </sv:property>
      <sv:property sv:name="mgnl:created" sv:type="Date">
        <sv:value>2015-02-26T16:14:31.990+01:00</sv:value>
      </sv:property>
      <sv:property sv:name="mgnl:createdBy" sv:type="String">
        <sv:value>superuser</sv:value>
      </sv:property>
      <sv:property sv:name="mgnl:lastActivated" sv:type="Date">
        <sv:value>2015-10-27T13:40:43.318+01:00</sv:value>
      </sv:property>
      <sv:property sv:name="mgnl:lastActivatedBy" sv:type="String">
        <sv:value>superuser</sv:value>
      </sv:property>
      <sv:property sv:name="mgnl:lastModified" sv:type="Date">
        <sv:value>2015-02-26T16:14:31.990+01:00</sv:value>
      </sv:property>
      <sv:property sv:name="mgnl:lastModifiedBy" sv:type="String">
        <sv:value>superuser</sv:value>
      </sv:property>
    </sv:node>
    <sv:node sv:name="footer3">
      <sv:property sv:name="jcr:primaryType" sv:type="Name">
        <sv:value>mgnl:area</sv:value>
      </sv:property>
      <sv:property sv:name="jcr:uuid" sv:type="String">
        <sv:value>7bb4b74d-2e42-43c0-948a-3fea95ca4d5e</sv:value>
      </sv:property>
      <sv:property sv:name="jcr:createdBy" sv:type="String">
        <sv:value>admin</sv:value>
      </sv:property>
      <sv:property sv:name="mgnl:activationStatus" sv:type="Boolean">
        <sv:value>true</sv:value>
      </sv:property>
      <sv:property sv:name="mgnl:created" sv:type="Date">
        <sv:value>2015-02-26T16:14:32.016+01:00</sv:value>
      </sv:property>
      <sv:property sv:name="mgnl:createdBy" sv:type="String">
        <sv:value>superuser</sv:value>
      </sv:property>
      <sv:property sv:name="mgnl:lastActivated" sv:type="Date">
        <sv:value>2015-10-27T13:40:43.318+01:00</sv:value>
      </sv:property>
      <sv:property sv:name="mgnl:lastActivatedBy" sv:type="String">
        <sv:value>superuser</sv:value>
      </sv:property>
      <sv:property sv:name="mgnl:lastModified" sv:type="Date">
        <sv:value>2015-02-26T16:14:32.016+01:00</sv:value>
      </sv:property>
      <sv:property sv:name="mgnl:lastModifiedBy" sv:type="String">
        <sv:value>superuser</sv:value>
      </sv:property>
    </sv:node>
    <sv:node sv:name="footer4">
      <sv:property sv:name="jcr:primaryType" sv:type="Name">
        <sv:value>mgnl:area</sv:value>
      </sv:property>
      <sv:property sv:name="jcr:uuid" sv:type="String">
        <sv:value>4c1103b5-01eb-4056-b999-6bc67a97b0de</sv:value>
      </sv:property>
      <sv:property sv:name="jcr:createdBy" sv:type="String">
        <sv:value>admin</sv:value>
      </sv:property>
      <sv:property sv:name="mgnl:activationStatus" sv:type="Boolean">
        <sv:value>true</sv:value>
      </sv:property>
      <sv:property sv:name="mgnl:created" sv:type="Date">
        <sv:value>2015-02-26T16:14:32.035+01:00</sv:value>
      </sv:property>
      <sv:property sv:name="mgnl:createdBy" sv:type="String">
        <sv:value>superuser</sv:value>
      </sv:property>
      <sv:property sv:name="mgnl:lastActivated" sv:type="Date">
        <sv:value>2015-10-27T13:40:43.318+01:00</sv:value>
      </sv:property>
      <sv:property sv:name="mgnl:lastActivatedBy" sv:type="String">
        <sv:value>superuser</sv:value>
      </sv:property>
      <sv:property sv:name="mgnl:lastModified" sv:type="Date">
        <sv:value>2015-02-26T16:14:32.035+01:00</sv:value>
      </sv:property>
      <sv:property sv:name="mgnl:lastModifiedBy" sv:type="String">
        <sv:value>superuser</sv:value>
      </sv:property>
    </sv:node>
    <sv:node sv:name="lastLinks">
      <sv:property sv:name="jcr:primaryType" sv:type="Name">
        <sv:value>mgnl:area</sv:value>
      </sv:property>
      <sv:property sv:name="jcr:uuid" sv:type="String">
        <sv:value>984b4a74-ea75-4676-88df-3b9e4330826c</sv:value>
      </sv:property>
      <sv:property sv:name="jcr:createdBy" sv:type="String">
        <sv:value>admin</sv:value>
      </sv:property>
      <sv:property sv:name="mgnl:activationStatus" sv:type="Boolean">
        <sv:value>true</sv:value>
      </sv:property>
      <sv:property sv:name="mgnl:created" sv:type="Date">
        <sv:value>2015-06-18T17:22:48.872+02:00</sv:value>
      </sv:property>
      <sv:property sv:name="mgnl:createdBy" sv:type="String">
        <sv:value>superuser</sv:value>
      </sv:property>
      <sv:property sv:name="mgnl:lastActivated" sv:type="Date">
        <sv:value>2015-10-27T13:40:43.318+01:00</sv:value>
      </sv:property>
      <sv:property sv:name="mgnl:lastActivatedBy" sv:type="String">
        <sv:value>superuser</sv:value>
      </sv:property>
      <sv:property sv:name="mgnl:lastModified" sv:type="Date">
        <sv:value>2015-06-18T17:22:48.872+02:00</sv:value>
      </sv:property>
      <sv:property sv:name="mgnl:lastModifiedBy" sv:type="String">
        <sv:value>superuser</sv:value>
      </sv:property>
    </sv:node>
  </sv:node>
</sv:node>
